{
  "annotations": {
    "changelogDate": "20250823222213"
  },
  "dto": "mapstruct",
  "fields": [
    {
      "fieldName": "name",
      "fieldType": "String",
      "fieldValidateRules": ["required"]
    },
    {
      "fieldName": "uniqueId",
      "fieldType": "String",
      "fieldValidateRules": ["unique"]
    },
    {
      "fieldName": "atcCode",
      "fieldType": "String"
    },
    {
      "fieldName": "officialUrl",
      "fieldType": "String"
    },
    {
      "fieldName": "active",
      "fieldType": "Boolean",
      "fieldValidateRules": ["required"]
    },
    {
      "fieldName": "created",
      "fieldType": "ZonedDateTime"
    },
    {
      "fieldName": "createdBy",
      "fieldType": "String"
    },
    {
      "fieldName": "updated",
      "fieldType": "ZonedDateTime"
    },
    {
      "fieldName": "updatedBy",
      "fieldType": "String"
    }
  ],
  "jpaMetamodelFiltering": false,
  "name": "Product",
  "pagination": "pagination",
  "readOnly": false,
  "relationships": [],
  "searchEngine": "no",
  "service": "serviceClass"
}
